{
	"storyName": "Week1lol",
	"difficulties": "hard",
	"hideFreeplay": false,
	"weekBackground": "",
	"weekBefore": "week1",
	"freeplayColor": [
		146,
		113,
		253
	],
	"startUnlocked": true,
	"hideStoryMode": false,
	"songs": [
		
		[
			"my-new-plaything",
			"1686458614550",
			[
				180,
				100,
				0
			]
		],
		[
			"my-spot",
			"113_sin_titulo_20230422215327",
			[
				255,
				255,
				255
			]
		],
		[
			"wooden-hand",
			"icon-Ventrilocuo",
			[
				180,
				100,
				0
			]
		]
	],
	"weekCharacters": [
		"",
		"",
		""
	],
	"hiddenUntilUnlocked": false,
	"weekName": "mi polla week"
}